aind_dynamic_foraging_models/__init__.py
aind_dynamic_foraging_models/generative_model/__init__.py
aind_dynamic_foraging_models/generative_model/act_functions.py
aind_dynamic_foraging_models/generative_model/base.py
aind_dynamic_foraging_models/generative_model/forager_compare_threshold.py
aind_dynamic_foraging_models/generative_model/forager_loss_counting.py
aind_dynamic_foraging_models/generative_model/forager_q_learning.py
aind_dynamic_foraging_models/generative_model/foragers.py
aind_dynamic_foraging_models/generative_model/learn_functions.py
aind_dynamic_foraging_models/generative_model/params/__init__.py
aind_dynamic_foraging_models/generative_model/params/forager_compare_threshold_params.py
aind_dynamic_foraging_models/generative_model/params/forager_loss_counting_params.py
aind_dynamic_foraging_models/generative_model/params/forager_q_learning_params.py
aind_dynamic_foraging_models/generative_model/params/util.py
aind_dynamic_foraging_models/logistic_regression/__init__.py
aind_dynamic_foraging_models/logistic_regression/model.py
aind_dynamic_foraging_models/logistic_regression/plot.py
aind_dynamic_foraging_models/logistic_regression/readme.md
aind_dynamic_foraging_models-0.13.0.dist-info/licenses/LICENSE
aind_dynamic_foraging_models-0.13.0.dist-info/METADATA
aind_dynamic_foraging_models-0.13.0.dist-info/WHEEL
aind_dynamic_foraging_models-0.13.0.dist-info/top_level.txt
aind_dynamic_foraging_models-0.13.0.dist-info/RECORD
