Metadata-Version: 2.4
Name: aind-dynamic-foraging-models
Version: 0.13.0
Summary: Generated from aind-library-template
Author: Allen Institute for Neural Dynamics
License: MIT
Classifier: Programming Language :: Python :: 3
Requires-Python: >=3.9
License-File: LICENSE
Requires-Dist: numpy
Requires-Dist: matplotlib
Requires-Dist: scikit-learn
Requires-Dist: scipy
Requires-Dist: pydantic
Provides-Extra: dev
Requires-Dist: black; extra == "dev"
Requires-Dist: coverage; extra == "dev"
Requires-Dist: flake8; extra == "dev"
Requires-Dist: interrogate; extra == "dev"
Requires-Dist: isort; extra == "dev"
Requires-Dist: Sphinx; extra == "dev"
Requires-Dist: furo; extra == "dev"
Requires-Dist: aind-behavior-gym; extra == "dev"
Requires-Dist: aind_dynamic_foraging_basic_analysis; extra == "dev"
Provides-Extra: rl
Requires-Dist: aind-behavior-gym; extra == "rl"
Requires-Dist: aind_dynamic_foraging_basic_analysis; extra == "rl"
Dynamic: license-file
